haumea/__init__.py
haumea/__main__.py
haumea/quickstart.py
haumea/quickstart/config.json
haumea/quickstart/content/about.html
haumea/quickstart/content/index.html
haumea/quickstart/content/sample.html
haumea/quickstart/layouts/_base.html
haumea/quickstart/layouts/_pagination.html
haumea/quickstart/layouts/partials/footer.html
haumea/quickstart/layouts/partials/head.html
haumea/quickstart/layouts/partials/header.html
haumea-0.72.4.dist-info/LICENSE
haumea-0.72.4.dist-info/METADATA
haumea-0.72.4.dist-info/WHEEL
haumea-0.72.4.dist-info/entry_points.txt
haumea-0.72.4.dist-info/top_level.txt
haumea-0.72.4.dist-info/RECORD
