Metadata-Version: 2.1
Name: haumea
Version: 0.72.4
Summary: Small & fast python library to build static websites
Home-page: https://github.com/guillbertrand/haumea
Author: Guillaume Betrand
Author-email: gbe.io@pm.me
License: UNKNOWN
Keywords: SSG graphql json python static website generator
Platform: UNKNOWN
Classifier: Programming Language :: Python :: 3
Classifier: License :: OSI Approved :: MIT License
Classifier: Operating System :: OS Independent
Classifier: Environment :: Console
Requires-Python: >=3.6
Requires-Dist: requests
Requires-Dist: watchdog
Requires-Dist: python-dateutil
